citepy/__init__.py
citepy/classes.py
citepy/cli.py
citepy/csl-data.json
citepy/validate.py
citepy/version.py
citepy/repos/__init__.py
citepy/repos/common.py
citepy/repos/cran.py
citepy/repos/crates.py
citepy/repos/pypi.py
citepy-0.5.0.dist-info/LICENSE
citepy-0.5.0.dist-info/METADATA
citepy-0.5.0.dist-info/WHEEL
citepy-0.5.0.dist-info/entry_points.txt
citepy-0.5.0.dist-info/top_level.txt
citepy-0.5.0.dist-info/RECORD
