Metadata-Version: 2.1
Name: citepy
Version: 0.5.0
Summary: Automatically create citations for packages
Home-page: https://www.github.com/clbarnes/citepy
Author: Chris L. Barnes
Author-email: cbarnes@mrc-lmb.cam.ac.uk
License: MIT
Platform: UNKNOWN
Requires-Python: >=3.7,<4
Requires-Dist: jsonschema
Requires-Dist: httpx
Requires-Dist: beautifulsoup4
